{"id":"01hvaffb5c1hzqwmyen2s2m857","add_time_ms":1712969985197,"type":"doc","_id":"110","char_count":{"word":250,"char_without_spaces":420,"char_with_spaces":483,"char_all":503},"title":"项目文件配置sass","content":"sass是css的扩展，语法更强大灵活，易于编写代码。\n需要在project.config.json文件中添加:\n    \"setting\": {\n      \"useCompilerPlugins\": [\n        \"sass\"\n      ],\n      ...\n    }\n   在创建项目的时候，每个项目的根目录生成两个config.json文件，用于保存开发者在工具上做的个性化配置，例如和编译有关的配置。\n  \n  当重新安装微信开发者工具或者换电脑工作时，只要载入同一个项目的代码包，开发者工具就会自动恢复到当时开发项目时的个性化配置。\n  \n  主要有以下2个配置文件来控制：\n  project.config.json：公共配置（共有配置或通用配置）\n  \n  \n  project.private.config.json：私有配置文件，主要用来个性化配置（个人习惯）\n  \n  注意事项:\n  1.project.private.config.josn写到.gitignore避免版本管理冲突。\n  2.与最终编译结果有的配置必须设置到project.config.json中。","edit_time_ms":1712971091045,"snapshots":[{"id":"01jdc8smakaa8q2seesxkhfwbc","item_id":"01hvaffb5c1hzqwmyen2s2m857","add_time_ms":1732357443923,"hash":"9da1b395e437c335ee8560f43340df99","length":503,"char_count_char_with_spaces":483,"char_count_char_without_spaces":420,"char_count_word":250,"version_key":1}]}